relay_sdk/__init__.py
relay_sdk/client.py
relay_sdk/decorators.py
relay_sdk/events.py
relay_sdk/interface.py
relay_sdk/outputs.py
relay_sdk/typing.py
relay_sdk/util.py
relay_sdk/webhook.py
relay_sdk/workflows.py
relay_sdk-0.3.1.dist-info/LICENSE.txt
relay_sdk-0.3.1.dist-info/METADATA
relay_sdk-0.3.1.dist-info/WHEEL
relay_sdk-0.3.1.dist-info/top_level.txt
relay_sdk-0.3.1.dist-info/RECORD
