Metadata-Version: 2.1
Name: relay-sdk
Version: 0.3.1
Summary: SDK for interacting with Puppet Relay
Home-page: https://github.com/puppetlabs/relay-sdk-python
Author: Puppet, Inc.
Author-email: relay@puppet.com
Classifier: Intended Audience :: Developers
Classifier: License :: OSI Approved :: Apache Software License
Requires-Python: >=3.8
License-File: LICENSE.txt
Requires-Dist: asgiref (>=3.2.7)
Requires-Dist: hypercorn (>=0.13.2)
Requires-Dist: requests (>=2.23)
